Workbook

Sheet Backlog Priorizado
A1: BACKLOG PRIORIZADO DEL PRODUCTO - MONOKERA APP
A2: Caso 10 - Monokera | Fase Técnica 1: Análisis | Líder: Santiago Arias Mosquera | Corte: 17 de septiembre de 2026
A3: Priorización MoSCoW combinada con relación Valor/Esfuerzo. Estimacion en puntos de historia (escala Fibonacci). El alcance del MVP corresponde a las historias 'Must have' y 'Should have'.
A5: ID | B5: Épica | C5: Historia de usuario | D5: Valor de negocio (1-5) | E5: Esfuerzo (pts) | F5: Ratio Valor/Esfuerzo | G5: Prioridad MoSCoW | H5: Orden | I5: Sprint asignado | J5: Estado | K5: Stakeholder que la exige
A6: HU-01 | B6: E8 - Gestión del proyecto | C6: Como equipo de proyecto necesito un acta de constitución aprobada para formalizar el alcance, los roles y las restricciones del proyecto. | D6: 5 | E6: 3 | F6: =D6/E6 -> 1.6666667 | G6: Must have | H6: =RANK(F6,$F$6:$F$48,0) -> 2 | I6: Sprint 1 | J6: Completado | K6: ST-05 Dirección General
A7: HU-02 | B7: E8 - Gestión del proyecto | C7: Como equipo de proyecto necesito un esquema metodológico justificado para gobernar la ejecución bajo incertidumbre regulatoria. | D7: 5 | E7: 3 | F7: =D7/E7 -> 1.6666667 | G7: Must have | H7: =RANK(F7,$F$6:$F$48,0) -> 2 | I7: Sprint 1 | J7: Completado | K7: ST-11 Docente
A8: HU-03 | B8: E8 - Gestión del proyecto | C8: Como gerente de proyecto necesito un cronograma con línea base para controlar fechas de fase y entregas quincenales. | D8: 5 | E8: 5 | F8: =D8/E8 -> 1 | G8: Must have | H8: =RANK(F8,$F$6:$F$48,0) -> 11 | I8: Sprint 1 | J8: Completado | K8: ST-05 Dirección General
A9: HU-04 | B9: E8 - Gestión del proyecto | C9: Como gerente de proyecto necesito el presupuesto distribuido y una tabla de costos unitarios para controlar la desviación presupuestal. | D9: 5 | E9: 5 | F9: =D9/E9 -> 1 | G9: Must have | H9: =RANK(F9,$F$6:$F$48,0) -> 11 | I9: Sprint 1 | J9: Completado | K9: ST-05 Dirección General
A10: HU-05 | B10: E8 - Gestión del proyecto | C10: Como equipo necesito una bitácora de reuniones para dejar trazabilidad de las decisiones tomadas con el cliente. | D10: 4 | E10: 2 | F10: =D10/E10 -> 2 | G10: Must have | H10: =RANK(F10,$F$6:$F$48,0) -> 1 | I10: Sprint 1 | J10: Completado | K10: ST-11 Docente
A11: HU-06 | B11: E7 - Cumplimiento y accesibilidad | C11: Como área legal necesito conocer el inventario de textos contractuales que se mostrarán en la aplicación para poder validarlos. | D11: 5 | E11: 3 | F11: =D11/E11 -> 1.6666667 | G11: Must have | H11: =RANK(F11,$F$6:$F$48,0) -> 2 | I11: Sprint 1 | J11: Completado | K11: ST-01 Legal
A12: HU-07 | B12: E1 - Resumen y estado de póliza | C12: Como asegurado quiero ver el resumen de mi póliza activa para saber de un vistazo qué tengo contratado. | D12: 5 | E12: 5 | F12: =D12/E12 -> 1 | G12: Must have | H12: =RANK(F12,$F$6:$F$48,0) -> 11 | I12: Sprint 1 | J12: Completado | K12: ST-06 Asegurado final
A13: HU-08 | B13: E1 - Resumen y estado de póliza | C13: Como asegurado quiero ver el estado de mi cobertura (activa, por vencer, vencida) para saber si estoy protegido hoy. | D13: 5 | E13: 3 | F13: =D13/E13 -> 1.6666667 | G13: Must have | H13: =RANK(F13,$F$6:$F$48,0) -> 2 | I13: Sprint 1 | J13: Completado | K13: ST-06 Asegurado final
A14: HU-09 | B14: E8 - Gestión del proyecto | C14: Como equipo necesito identificar y clasificar los stakeholders para definir la estrategia de relacionamiento de cada uno. | D14: 5 | E14: 3 | F14: =D14/E14 -> 1.6666667 | G14: Must have | H14: =RANK(F14,$F$6:$F$48,0) -> 2 | I14: Sprint 1 | J14: Completado | K14: ST-10 Equipo de proyecto
A15: HU-10 | B15: E2 - Primas, coberturas y exclusiones | C15: Como área actuarial necesito que se documente que el prototipo no altera el modelo actuarial ni las tarifas reales. | D15: 5 | E15: 3 | F15: =D15/E15 -> 1.6666667 | G15: Must have | H15: =RANK(F15,$F$6:$F$48,0) -> 2 | I15: Sprint 1 | J15: No completado | K15: ST-02 Actuaría
A16: HU-11 | B16: E1 - Resumen y estado de póliza | C16: Como asegurado quiero ver el historial de mi cobertura para entender cómo ha cambiado mi póliza en el tiempo. | D16: 3 | E16: 5 | F16: =D16/E16 -> 0.6 | G16: Should have | H16: =RANK(F16,$F$6:$F$48,0) -> 29 | I16: Sprint 1 | J16: No completado | K16: ST-06 Asegurado final
A17: HU-12 | B17: E2 - Primas, coberturas y exclusiones | C17: Como asegurado quiero consultar el detalle de mis coberturas para saber exactamente qué cubre mi póliza. | D17: 5 | E17: 8 | F17: =D17/E17 -> 0.625 | G17: Must have | H17: =RANK(F17,$F$6:$F$48,0) -> 24 | I17: Sprint 2 | J17: Completado | K17: ST-06 Asegurado final
... A48: HU-43 | B48: E1 - Resumen y estado de póliza | C48: Como asegurado quiero integrar mis pólizas de otras aseguradoras no partner. | D48: 2 | E48: 21 | F48: =D48/E48 -> 0.095238095 | G48: Won't have (MVP) | H48: =RANK(F48,$F$6:$F$48,0) -> 43 | I48: Backlog | J48: Pendiente | K48: ST-06 Asegurado final
A49: =COUNTA(A6:A48) -> 43 | C49: TOTALES | E49: =SUM(E6:E48) -> 305
B51: RESUMEN DE PRIORIZACIÓN
D52: Cantidad | E52: Puntos
B53: Historias 'Must have': | D53: =COUNTIF(G6:G48,"Must have") -> 25 | E53: =SUMIF(G6:G48,"Must have",E6:E48) -> 140
B54: Historias 'Should have': | D54: =COUNTIF(G6:G48,"Should have") -> 11 | E54: =SUMIF(G6:G48,"Should have",E6:E48) -> 73
B55: Historias 'Could have': | D55: =COUNTIF(G6:G48,"Could have") -> 4 | E55: =SUMIF(G6:G48,"Could have",E6:E48) -> 29
B56: Historias fuera del MVP: | D56: =COUNTIF(G6:G48,"Won't have (MVP)") -> 3 | E56: =SUMIF(G6:G48,"Won't have (MVP)",E6:E48) -> 63
B58: Alcance comprometido del MVP = historias 'Must have' + 'Should have'. Las 'Could have' se construyen solo si el avance lo permite y las 'Won't have' quedan documentadas como alcance futuro para evitar reclamos de cambio no gestionado.

Sheet Indicador Sprint
A1: INDICADOR 1 - DESEMPEÑO: CUMPLIMIENTO DE SPRINT (%)
A2: Fórmula: C = (HC / HCO) * 100 | HC = Historias Completadas, HCO = Historias Comprometidas | Meta mínima: 80%
A3: Los valores de HC y HCO se calculan directamente desde la hoja 'Backlog Priorizado'.
A5: Sprint | B5: Periodo | C5: Historias Comprometidas (HCO) | D5: Historias Completadas (HC) | E5: Cumplimiento (C%) | F5: Estado vs. meta 80% | G5: Historias no completadas | H5: Análisis de causa
A6: Sprint 1 | B6: 28 ago - 10 sep 2026 | C6: =COUNTIF('Backlog Priorizado'!$I$6:$I$48,A6) -> 11 | D6: =COUNTIFS('Backlog Priorizado'!$I$6:$I$48,A6,'Backlog Priorizado'!$J$6:$J$48,"Completado") -> 9 | E6: =IF(OR(C6=0,COUNTIFS('Backlog Priorizado'!$I$6:$I$48,A6,'Backlog Priorizado'!$J$6:$J$48,"Pendiente")=C6),"",D6/C6) -> 0.81818182 | F6: =IF(E6="","Pendiente",IF(E6>=0.8,"CUMPLE","NO CUMPLE")) -> CUMPLE | G6: HU-10, HU-11 | H6: HU-10 se retrasó por la demora en contratar al consultor actuarial externo. HU-11 se despriorizó para no comprometer las historias 'Must have' del sprint.
A7: Sprint 2 | B7: 11 sep - 24 sep 2026 | C7: =COUNTIF('Backlog Priorizado'!$I$6:$I$48,A7) -> 12 | D7: =COUNTIFS('Backlog Priorizado'!$I$6:$I$48,A7,'Backlog Priorizado'!$J$6:$J$48,"Completado") -> 10 | E7: =IF(OR(C7=0,COUNTIFS('Backlog Priorizado'!$I$6:$I$48,A7,'Backlog Priorizado'!$J$6:$J$48,"Pendiente")=C7),"",D7/C7) -> 0.83333333 | F7: =IF(E7="","Pendiente",IF(E7>=0.8,"CUMPLE","NO CUMPLE")) -> CUMPLE | G7: HU-22, HU-23 | H7: HU-22 depende del cierre de HU-10. HU-23 fue subestimada: el flujo de siniestros exige validación legal adicional que no se dimensionó al planificar.
A8: Sprint 3 | B8: 25 sep - 08 oct 2026 | C8: =COUNTIF('Backlog Priorizado'!$I$6:$I$48,A8) -> 7 | D8: =COUNTIFS('Backlog Priorizado'!$I$6:$I$48,A8,'Backlog Priorizado'!$J$6:$J$48,"Completado") -> 0 | E8: =IF(OR(C8=0,COUNTIFS('Backlog Priorizado'!$I$6:$I$48,A8,'Backlog Priorizado'!$J$6:$J$48,"Pendiente")=C8),"",D8/C8) | F8: =IF(E8="","Pendiente",IF(E8>=0.8,"CUMPLE","NO CUMPLE")) -> Pendiente | H8: Sprint en planificación.
A9: Sprint 4 | B9: 09 oct - 22 oct 2026 | C9: =COUNTIF('Backlog Priorizado'!$I$6:$I$48,A9) -> 5 | D9: =COUNTIFS('Backlog Priorizado'!$I$6:$I$48,A9,'Backlog Priorizado'!$J$6:$J$48,"Completado") -> 0 | E9: =IF(OR(C9=0,COUNTIFS('Backlog Priorizado'!$I$6:$I$48,A9,'Backlog Priorizado'!$J$6:$J$48,"Pendiente")=C9),"",D9/C9) | F9: =IF(E9="","Pendiente",IF(E9>=0.8,"CUMPLE","NO CUMPLE")) -> Pendiente | H9: Sprint en planificación.
A10: Sprint 5 | B10: 23 oct - 05 nov 2026 | C10: =COUNTIF('Backlog Priorizado'!$I$6:$I$48,A10) -> 3 | D10: =COUNTIFS('Backlog Priorizado'!$I$6:$I$48,A10,'Backlog Priorizado'!$J$6:$J$48,"Completado") -> 0 | E10: =IF(OR(C10=0,COUNTIFS('Backlog Priorizado'!$I$6:$I$48,A10,'Backlog Priorizado'!$J$6:$J$48,"Pendiente")=C10),"",D10/C10) | F10: =IF(E10="","Pendiente",IF(E10>=0.8,"CUMPLE","NO CUMPLE")) -> Pendiente | H10: Sprint en planificación.
A11: Sprint 6 | B11: 06 nov - 19 nov 2026 | C11: =COUNTIF('Backlog Priorizado'!$I$6:$I$48,A11) -> 2 | D11: =COUNTIFS('Backlog Priorizado'!$I$6:$I$48,A11,'Backlog Priorizado'!$J$6:$J$48,"Completado") -> 0 | E11: =IF(OR(C11=0,COUNTIFS('Backlog Priorizado'!$I$6:$I$48,A11,'Backlog Priorizado'!$J$6:$J$48,"Pendiente")=C11),"",D11/C11) | F11: =IF(E11="","Pendiente",IF(E11>=0.8,"CUMPLE","NO CUMPLE")) -> Pendiente | H11: Sprint en planificación.
B12: ACUMULADO DEL PROYECTO | C12: =SUM(C6:C11) -> 40 | D12: =SUM(D6:D11) -> 19
A14: CORTE SEGUIMIENTO 1 (21 al 26 de septiembre de 2026) - SPRINTS 1 Y 2
A15: Historias comprometidas acumuladas (HCO): | D15: =C6+C7 -> 23
A16: Historias completadas acumuladas (HC): | D16: =D6+D7 -> 19
A17: Cumplimiento de Sprint acumulado (C%): | D17: =(D6+D7)/(C6+C7) -> 0.82608696
A18: Meta mínima exigida: | D18: 0.8
A19: Estado del indicador: | D19: =IF((D6+D7)/(C6+C7)>=0.8,"CUMPLE LA META","NO CUMPLE LA META") -> CUMPLE LA META
A21: Acción correctiva adoptada: las cuatro historias no completadas (HU-10, HU-11, HU-22, HU-23) se trasladan al Sprint 3 como deuda del backlog. Para absorberlas sin volver a incumplir la meta, HU-30 y HU-37 se desplazan a sprints posteriores, de modo que el compromiso neto de historias nuevas del Sprint 3 se reduce en lugar de aumentar.
