Workbook

Sheet Costos Unitarios
A1: TABLA DE COSTOS UNITARIOS - PROYECTO MONOKERA APP
A2: Caso 10 - Monokera | Prototipo Navegable de Alta Fidelidad | Presupuesto asignado: $265.000.000 COP | Desviación máxima permitida: +/-10%
A3: Valores en pesos colombianos (COP). Tarifas definidas por el equipo en la fase de Planeación tomando como referencia el mercado colombiano de servicios digitales 2026.
A5: Item | B5: Categoría Presupuestal | C5: Concepto / Recurso | D5: Unidad de Medida | E5: Cantidad | F5: Costo Unitario (COP) | G5: Costo Total (COP) | H5: % del Presupuesto | I5: Justificación
A6: 1 | B6: 1. Horas Hombre | C6: Líder de Análisis / Analista Senior | D6: Hora | E6: 240 | F6: 85000 | G6: =E6*F6 -> 20400000 | H6: =G6/$G$35 -> 0.076981132 | I6: Levantamiento de requisitos, historias de usuario y backlog priorizado del MVP.
A7: 2 | B7: 1. Horas Hombre | C7: Analista de Requisitos | D7: Hora | E7: 200 | F7: 60000 | G7: =E7*F7 -> 12000000 | H7: =G7/$G$35 -> 0.045283019 | I7: Elicitación con las áreas legal, actuarial y comercial; trazabilidad de requisitos.
A8: 3 | B8: 1. Horas Hombre | C8: Arquitecto de Información | D8: Hora | E8: 160 | F8: 72000 | G8: =E8*F8 -> 11520000 | H8: =G8/$G$35 -> 0.043471698 | I8: Estructura de navegación y jerarquia de contenidos de póliza.
A9: 4 | B9: 1. Horas Hombre | C9: Diseñador de Interacción (prototipado navegable) | D9: Hora | E9: 320 | F9: 75000 | G9: =E9*F9 -> 24000000 | H9: =G9/$G$35 -> 0.090566038 | I9: Construcción de los flujos navegables de alta fidelidad.
A10: 5 | B10: 1. Horas Hombre | C10: Especialista en Prototipado / GUI | D10: Hora | E10: 300 | F10: 65000 | G10: =E10*F10 -> 19500000 | H10: =G10/$G$35 -> 0.073584906 | I10: Ensamble de componentes, estados y microinteracciones del prototipo.
A11: 6 | B11: 1. Horas Hombre | C11: Analista de Contenidos | D11: Hora | E11: 150 | F11: 50000 | G11: =E11*F11 -> 7500000 | H11: =G11/$G$35 -> 0.028301887 | I11: Redacción de los mensajes educativos sobre protección y uso responsable del seguro.
A12: 7 | B12: 1. Horas Hombre | C12: Especialista en Microcopy Regulado | D12: Hora | E12: 120 | F12: 58000 | G12: =E12*F12 -> 6960000 | H12: =G12/$G$35 -> 0.026264151 | I12: Redacción de textos contractuales aprobables por Legal bajo normativa SFC.
A13: 8 | B13: 2. Diseño UX/UI | C13: Investigación UX (entrevistas y benchmark) | D13: Hora | E13: 120 | F13: 75000 | G13: =E13*F13 -> 9000000 | H13: =G13/$G$35 -> 0.033962264 | I13: 12 entrevistas a asegurados y análisis competitivo de aplicaciones de seguros.
A14: 9 | B14: 2. Diseño UX/UI | C14: Diseño visual y Design System | D14: Hora | E14: 220 | F14: 75000 | G14: =E14*F14 -> 16500000 | H14: =G14/$G$35 -> 0.062264151 | I14: Sistema de componentes reutilizable alineado a la marca Monokera.
A15: 10 | B15: 2. Diseño UX/UI | C15: Diseño de pantallas de alta fidelidad | D15: Hora | E15: 400 | F15: 70000 | G15: =E15*F15 -> 28000000 | H15: =G15/$G$35 -> 0.10566038 | I15: Aproximadamente 45 pantallas del MVP con sus estados y variantes.
A16: 11 | B16: 2. Diseño UX/UI | C16: Diseño del simulador de planes de cobertura | D16: Hora | E16: 100 | F16: 70000 | G16: =E16*F16 -> 7000000 | H16: =G16/$G$35 -> 0.026415094 | I16: Componente crítico: simulación de cambio y ampliación de cobertura sin alterar tarifas reales.
A17: 12 | B17: 2. Diseño UX/UI | C17: Licencia de herramienta de diseño colaborativo | D17: Usuario-mes | E17: 12 | F17: 75000 | G17: =E17*F17 -> 900000 | H17: =G17/$G$35 -> 0.0033962264 | I17: 4 usuarios durante los 3 meses de proyecto.
... A34: 29 | B34: 6. Contingencias Actuariales y Regulatorias | C34: Reserva de contingencia regulatoria | D34: Global | E34: 1 | F34: 9990000 | G34: =E34*F34 -> 9990000 | H34: =G34/$G$35 -> 0.037698113 | I34: Colchón para cambios normativos y re-trabajo derivado de nuevas circulares de la SFC.
A35: TOTAL PRESUPUESTO PLANIFICADO | G35: =SUM(G6:G34) -> 265000000 | H35: =SUM(H6:H34) -> 1
B37: Presupuesto asignado por el cliente: | G37: 265000000
B38: Diferencia (debe ser $0): | G38: =G35-G37 -> 0
B40: Convención: celdas en AZUL = datos de entrada (cantidades y tarifas). Celdas en NEGRO = calculadas por fórmula.

Sheet Distribución Presupuestal
A1: DISTRIBUCIÓN DEL PRESUPUESTO POR CATEGORÍA
A2: Categorías obligatorias definidas en el numeral 3.6 del documento del caso.
A4: Categoría Presupuestal | B4: Costo Planificado (COP) | C4: % del Total | D4: Criterio de Asignación
A5: 1. Horas Hombre | B5: =SUMIF('Costos Unitarios'!$B$6:$B$34,A5,'Costos Unitarios'!$G$6:$G$34) -> 101880000 | C5: =B5/$B$11 -> 0.38445283 | D5: Mayor peso del presupuesto: el producto es un prototipo navegable, por lo que el esfuerzo humano de análisis y construcción concentra el valor entregado.
A6: 2. Diseño UX/UI | B6: =SUMIF('Costos Unitarios'!$B$6:$B$34,A6,'Costos Unitarios'!$G$6:$G$34) -> 70300000 | C6: =B6/$B$11 -> 0.26528302 | D6: El objeto del caso es traducir información actuarial y contractual compleja en interfaces comprensibles; el diseño es el nucleo de la solucion.
A7: 3. Validación de Usabilidad | B7: =SUMIF('Costos Unitarios'!$B$6:$B$34,A7,'Costos Unitarios'!$G$6:$G$34) -> 22500000 | C7: =B7/$B$11 -> 0.08490566 | D7: El cliente exige reducción del abandono de pólizas; sin evidencia de comprensión del usuario no se puede sustentar el impacto.
A8: 4. Gestión del Proyecto | B8: =SUMIF('Costos Unitarios'!$B$6:$B$34,A8,'Costos Unitarios'!$G$6:$G$34) -> 26480000 | C8: =B8/$B$11 -> 0.099924528 | D8: Seguimiento quincenal obligatorio, control de dos indicadores y gestión de cuatro grupos de stakeholders con intereses en tensión.
A9: 5. Documentación | B9: =SUMIF('Costos Unitarios'!$B$6:$B$34,A9,'Costos Unitarios'!$G$6:$G$34) -> 17650000 | C9: =B9/$B$11 -> 0.066603774 | D9: Entorno regulado: la trazabilidad documental es exigida por Legal y es criterio explicito de evaluación del proyecto.
A10: 6. Contingencias Actuariales y Regulatorias | B10: =SUMIF('Costos Unitarios'!$B$6:$B$34,A10,'Costos Unitarios'!$G$6:$G$34) -> 26190000 | C10: =B10/$B$11 -> 0.098830189 | D10: Riesgo alto de cambios en circulares de la SFC durante la ejecución; el caso declara nivel de incertidumbre Medio-Alto.
A11: TOTAL | B11: =SUM(B5:B10) -> 265000000 | C11: =SUM(C5:C10) -> 1
A13: Validación contra el presupuesto asignado ($265.000.000): | B13: =B11-265000000 -> 0

Sheet Seguimiento Quincenal
A1: SEGUIMIENTO QUINCENAL DEL GASTO - INDICADOR 2 (EFICIENCIA)
A2: Desviación Presupuestal: D = ((CR - CP) / CP) * 100 | Meta máxima permitida del caso: +/-10%
A4: Quincena | B4: Periodo | C4: Costo Planificado (CP) | D4: Costo Real (CR) | E4: CP Acumulado | F4: CR Acumulado | G4: Desviación Acum. (D%) | H4: Estado vs. meta | I4: Observacion
A5: Q1 | B5: 28 ago - 10 sep 2026 | C5: 24800000 | D5: 25400000 | E5: =SUM($C$5:C5) -> 24800000 | F5: =IF(D5="","",SUM($D$5:D5)) -> 25400000 | G5: =IF(F5="","",(F5-E5)/E5) -> 0.024193548 | H5: =IF(G5="","Pendiente",IF(ABS(G5)<=0.1,"DENTRO DE META","FUERA DE META")) -> DENTRO DE META | I5: Planeación y arranque de Análisis. Sobrecosto menor por demora en la contratación del consultor actuarial.
A6: Q2 | B6: 11 sep - 24 sep 2026 | C6: 33600000 | D6: 36500000 | E6: =SUM($C$5:C6) -> 58400000 | F6: =IF(D6="","",SUM($D$5:D6)) -> 61900000 | G6: =IF(F6="","",(F6-E6)/E6) -> 0.059931507 | H6: =IF(G6="","Pendiente",IF(ABS(G6)<=0.1,"DENTRO DE META","FUERA DE META")) -> DENTRO DE META | I6: Cierre de Análisis. Sobrecosto en asesoria legal: Legal exigió doble revisión de los textos de exclusiones.
A7: Q3 | B7: 25 sep - 08 oct 2026 | C7: 42300000 | E7: =SUM($C$5:C7) -> 100700000 | F7: =IF(D7="","",SUM($D$5:D7)) | G7: =IF(F7="","",(F7-E7)/E7) | H7: =IF(G7="","Pendiente",IF(ABS(G7)<=0.1,"DENTRO DE META","FUERA DE META")) -> Pendiente | I7: Proyectado - fase de Diseño.
A8: Q4 | B8: 09 oct - 22 oct 2026 | C8: 55800000 | E8: =SUM($C$5:C8) -> 156500000 | F8: =IF(D8="","",SUM($D$5:D8)) | G8: =IF(F8="","",(F8-E8)/E8) | H8: =IF(G8="","Pendiente",IF(ABS(G8)<=0.1,"DENTRO DE META","FUERA DE META")) -> Pendiente | I8: Proyectado - Diseño e inicio de Implementación del prototipo.
A9: Q5 | B9: 23 oct - 05 nov 2026 | C9: 62400000 | E9: =SUM($C$5:C9) -> 218900000 | F9: =IF(D9="","",SUM($D$5:D9)) | G9: =IF(F9="","",(F9-E9)/E9) | H9: =IF(G9="","Pendiente",IF(ABS(G9)<=0.1,"DENTRO DE META","FUERA DE META")) -> Pendiente | I9: Proyectado - Implementación y arranque de Pruebas.
A10: Q6 | B10: 06 nov - 19 nov 2026 | C10: 46100000 | E10: =SUM($C$5:C10) -> 265000000 | F10: =IF(D10="","",SUM($D$5:D10)) | G10: =IF(F10="","",(F10-E10)/E10) | H10: =IF(G10="","Pendiente",IF(ABS(G10)<=0.1,"DENTRO DE META","FUERA DE META")) -> Pendiente | I10: Proyectado - Pruebas, Implantación y cierre del proyecto.
B11: TOTAL PROYECTO | C11: =SUM(C5:C10) -> 265000000 | D11: =SUM(D5:D10) -> 61900000
B13: Validación: el CP total debe igualar la Tabla de Costos Unitarios | G13: =C11-'Costos Unitarios'!G35 -> 0
B15: CORTE SEGUIMIENTO 1 (21 al 26 de septiembre de 2026)
B16: Costo Planificado acumulado (CP): | D16: =E6 -> 58400000
B17: Costo Real acumulado (CR): | D17: =F6 -> 61900000
B18: Desviación Presupuestal (D%): | D18: =G6 -> 0.059931507
B19: Estado frente a la meta (+/-10%): | D19: =H6 -> DENTRO DE META
B21: Nota: las celdas AMARILLAS de la columna CR se diligencian al cierre de cada quincena. Celdas AZULES = datos de entrada.
